sintellix/__init__.py
sintellix/core.py
sintellix/models.py
sintellix/training.py
sintellix/utils.py
sintellix-0.1.0.dist-info/METADATA
sintellix-0.1.0.dist-info/WHEEL
sintellix-0.1.0.dist-info/top_level.txt
sintellix-0.1.0.dist-info/RECORD
