Metadata-Version: 2.4
Name: sintellix
Version: 0.1.0
Summary: High-Performance Neural Network Framework with 3D Grid Architecture
Home-page: https://github.com/sintellix/sintellix
Author: randomdevel0per, Anthropic Claude Sonnet 4.5
Author-email: "randomdevel0per, Anthropic Claude Sonnet 4.5" <noreply@anthropic.com>
License: MIT
Project-URL: Homepage, https://github.com/sintellix/sintellix
Project-URL: Documentation, https://sintellix.readthedocs.io
Project-URL: Repository, https://github.com/sintellix/sintellix
Project-URL: Issues, https://github.com/sintellix/sintellix/issues
Keywords: neural-networks,cuda,deep-learning,attention,vq-gan
Classifier: Development Status :: 3 - Alpha
Classifier: Intended Audience :: Developers
Classifier: Intended Audience :: Science/Research
Classifier: License :: OSI Approved :: MIT License
Classifier: Programming Language :: Python :: 3
Classifier: Programming Language :: Python :: 3.8
Classifier: Programming Language :: Python :: 3.9
Classifier: Programming Language :: Python :: 3.10
Classifier: Programming Language :: Python :: 3.11
Classifier: Programming Language :: C++
Classifier: Topic :: Scientific/Engineering :: Artificial Intelligence
Requires-Python: >=3.8
Requires-Dist: numpy>=1.20.0
Requires-Dist: protobuf>=3.20.0
Provides-Extra: dev
Requires-Dist: pytest>=7.0.0; extra == "dev"
Requires-Dist: black>=22.0.0; extra == "dev"
Requires-Dist: flake8>=4.0.0; extra == "dev"
Requires-Dist: mypy>=0.950; extra == "dev"
Provides-Extra: docs
Requires-Dist: sphinx>=4.0.0; extra == "docs"
Requires-Dist: sphinx-rtd-theme>=1.0.0; extra == "docs"
Dynamic: author
Dynamic: home-page
Dynamic: requires-python
